Metadata-Version: 2.1
Name: yyjdgui
Version: 1.1.1062
Summary: yyjdgui for lyy
Author: lyy
Author-email: 
License: MIT
License-File: LICENSE
